{"took_ms":340,"used_vectors":true,"results":[{"listing_id":"retreat_1","title":"This listing","address":null,"price":1065.0,"rank":1,"score":0.563,"compatibility":97,"rationale":"This listing: near your target area while high safety rating. — 97% match."},{"listing_id":"hub_2","title":"This listing","address":null,"price":1355.0,"rank":2,"score":0.5585,"compatibility":94,"rationale":"This listing: high safety rating, plus near your target area. — 94% match."},{"listing_id":"windsorhills_2","title":"This listing","address":null,"price":1455.0,"rank":3,"score":0.549,"compatibility":88,"rationale":"This listing: good walkability while high safety rating. — 88% match."},{"listing_id":"edge_1","title":"This listing","address":null,"price":880.0,"rank":4,"score":0.5475,"compatibility":89,"rationale":"This listing: high safety rating while near your target area. — 89% match."},{"listing_id":"windsorhills_3","title":"This listing","address":null,"price":995.0,"rank":5,"score":0.5355,"compatibility":83,"rationale":"This listing: good walkability. high safety rating. — 83% match."},{"listing_id":"chasewood_1","title":"This listing","address":null,"price":1255.0,"rank":6,"score":0.5265,"compatibility":78,"rationale":"This listing: near your target area, plus high safety rating. — 78% match."},{"listing_id":"foxridge_1","title":"This listing","address":null,"price":640.0,"rank":7,"score":0.5255,"compatibility":79,"rationale":"This listing: near your target area. solid overall fit. — 79% match."},{"listing_id":"village_1","title":"This listing","address":null,"price":759.0,"rank":8,"score":0.5185,"compatibility":76,"rationale":"This listing: near your target area; also good walkability. — 76% match."},{"listing_id":"windsorhills_1","title":"This listing","address":null,"price":1110.0,"rank":9,"score":0.518,"compatibility":75,"rationale":"This listing: high safety rating. near your target area. — 75% match."},{"listing_id":"house_washington_1","title":"This listing","address":null,"price":2600.0,"rank":10,"score":0.517,"compatibility":74,"rationale":"This listing: good walkability; also near your target area. — 74% match."},{"listing_id":"house_huckleberry_1","title":"This listing","address":null,"price":2550.0,"rank":11,"score":0.5165,"compatibility":76,"rationale":"This listing: near your target area & high safety rating — 76% match."},{"listing_id":"foxridge_3","title":"This listing","address":null,"price":1100.0,"rank":12,"score":0.5105,"compatibility":71,"rationale":"This listing: near your target area. high safety rating. — 71% match."}],"hexes":[{"h3":"882a8a8b25fffff","lat":37.252059667995944,"lng":-80.36033035975345,"count":1,"weight":0.25,"price_avg":1065.0,"safety_avg":0.86,"compat_max":97},{"h3":"882a8ac66dfffff","lat":37.24848591161805,"lng":-80.46371417758225,"count":1,"weight":0.3647959183673469,"price_avg":1355.0,"safety_avg":0.8,"compat_max":94},{"h3":"882a8ac62bfffff","lat":37.22079927725677,"lng":-80.46091782843887,"count":2,"weight":0.3278061224489796,"price_avg":1282.5,"safety_avg":0.775,"compat_max":88},{"h3":"882a8ad6b5fffff","lat":37.28711094746502,"lng":-80.36633036078317,"count":1,"weight":0.25,"price_avg":880.0,"safety_avg":0.84,"compat_max":89},{"h3":"882a8ac607fffff","lat":37.21912592797466,"lng":-80.45063436004062,"count":1,"weight":0.25,"price_avg":995.0,"safety_avg":0.8,"compat_max":83},{"h3":"882a8a89e5fffff","lat":37.17971578909793,"lng":-80.37592228185761,"count":1,"weight":0.3137755102040816,"price_avg":1255.0,"safety_avg":0.88,"compat_max":78},{"h3":"882a8ac641fffff","lat":37.243462284411216,"lng":-80.43284769622586,"count":1,"weight":0.5,"price_avg":640.0,"safety_avg":0.69,"compat_max":79},{"h3":"882a8ad499fffff","lat":37.253741576948784,"lng":-80.3706184911302,"count":1,"weight":0.25,"price_avg":759.0,"safety_avg":0.61,"compat_max":76},{"h3":"882a8ad491fffff","lat":37.248078300779326,"lng":-80.37764774311576,"count":1,"weight":1.0,"price_avg":2600.0,"safety_avg":0.64,"compat_max":74},{"h3":"882a8ac617fffff","lat":37.202775646920976,"lng":-80.43382083122131,"count":1,"weight":0.9744897959183674,"price_avg":2550.0,"safety_avg":0.84,"compat_max":76},{"h3":"882a8ac66bfffff","lat":37.23947105703625,"lng":-80.45015494198125,"count":1,"weight":0.25,"price_avg":1100.0,"safety_avg":0.72,"compat_max":71}]}